optimus/__init__.py
optimus/_version.py
optimus/expressions.py
optimus/functions.py
optimus/infer.py
optimus/infer_spark.py
optimus/optimus.py
optimus/css/__init__.py
optimus/css/styles.css
optimus/engines/__init__.py
optimus/engines/base/__init__.py
optimus/engines/base/basedataframe.py
optimus/engines/base/columns.py
optimus/engines/base/constants.py
optimus/engines/base/create.py
optimus/engines/base/engine.py
optimus/engines/base/functions.py
optimus/engines/base/mask.py
optimus/engines/base/meta.py
optimus/engines/base/profile.py
optimus/engines/base/remote.py
optimus/engines/base/rows.py
optimus/engines/base/set.py
optimus/engines/base/stringclustering.py
optimus/engines/base/commons/__init__.py
optimus/engines/base/commons/functions.py
optimus/engines/base/cudf/__init__.py
optimus/engines/base/cudf/columns.py
optimus/engines/base/cudf/dataframe.py
optimus/engines/base/cudf/functions.py
optimus/engines/base/cudf/rows.py
optimus/engines/base/dask/__init__.py
optimus/engines/base/dask/columns.py
optimus/engines/base/dask/constants.py
optimus/engines/base/dask/dataframe.py
optimus/engines/base/dask/functions.py
optimus/engines/base/dask/rows.py
optimus/engines/base/dask/io/__init__.py
optimus/engines/base/dask/io/jdbc.py
optimus/engines/base/dataframe/__init__.py
optimus/engines/base/dataframe/columns.py
optimus/engines/base/dataframe/constants.py
optimus/engines/base/dataframe/dataframe.py
optimus/engines/base/dataframe/functions.py
optimus/engines/base/dataframe/rows.py
optimus/engines/base/distributed/__init__.py
optimus/engines/base/distributed/columns.py
optimus/engines/base/distributed/constants.py
optimus/engines/base/distributed/dataframe.py
optimus/engines/base/distributed/functions.py
optimus/engines/base/distributed/rows.py
optimus/engines/base/distributed/io/__init__.py
optimus/engines/base/distributed/io/jdbc.py
optimus/engines/base/io/__init__.py
optimus/engines/base/io/connect.py
optimus/engines/base/io/driver_context.py
pyoptimus-23.5.0b0.dist-info/LICENSE
pyoptimus-23.5.0b0.dist-info/METADATA
pyoptimus-23.5.0b0.dist-info/WHEEL
pyoptimus-23.5.0b0.dist-info/top_level.txt
pyoptimus-23.5.0b0.dist-info/RECORD
