Metadata-Version: 2.1
Name: pyoptimus
Version: 23.5.0b0
Summary: Optimus is the missing framework for cleaning and pre-processing data in a distributed fashion.
Home-page: https://github.com/hi-primus/optimus/
Author: Argenis Leon
Author-email: argenisleon@gmail.com
License: APACHE
Keywords: datacleaner,data-wrangling,data-cleansing,data-profiling
Platform: UNKNOWN
Classifier: Development Status :: 5 - Production/Stable
Classifier: Intended Audience :: Developers
Classifier: Topic :: Scientific/Engineering :: Artificial Intelligence
Classifier: License :: OSI Approved :: Apache Software License
Classifier: Programming Language :: Python :: 3.7
Classifier: Programming Language :: Python :: 3.8
Requires-Dist: pandas (==1.3.5)
Requires-Dist: numpy (>=1.21.2)
Requires-Dist: nltk (>=3.6.2)
Requires-Dist: requests (>=2.24.0)
Requires-Dist: fastnumbers (>=3.1.0)
Requires-Dist: setuptools (>=50.3.1)
Requires-Dist: Jinja2 (>=3.0.1)
Requires-Dist: humanize (>=3.9.0)
Requires-Dist: deepdiff (>=5.5.0)
Requires-Dist: glom (>=22.1.0)
Requires-Dist: statsmodels (>=0.13.1)
Requires-Dist: fast-histogram (>=0.10)
Requires-Dist: rply (>=0.7.8)
Requires-Dist: tabulate (>=0.8.9)
Requires-Dist: matplotlib (>=3.4.2)
Requires-Dist: seaborn (>=0.11.1)
Requires-Dist: jellyfish (>=0.8.7)
Requires-Dist: Metaphone (==0.6)
Requires-Dist: num2words (==0.5.10)
Requires-Dist: hi-dateinfer
Requires-Dist: hi-urlparser
Requires-Dist: yellowbrick
Requires-Dist: openpyxl (>=3.0.7)
Requires-Dist: xlrd (>=2.0.1)
Requires-Dist: fastavro (>=1.4.1)
Requires-Dist: pandavro (>=1.6.0)
Requires-Dist: pybigquery (>=0.10.1)
Requires-Dist: python-snappy (>=0.6.0)
Requires-Dist: s3fs (>=2021.7.0)
Requires-Dist: aiobotocore[boto3] (>=1.3.3)
Provides-Extra: ai
Requires-Dist: tensorflow (==2.9.1) ; extra == 'ai'
Requires-Dist: keras (>=2.6.0) ; extra == 'ai'
Requires-Dist: nltk (>=3.4.5) ; extra == 'ai'
Provides-Extra: all
Requires-Dist: pyspark (>=2.4.1) ; extra == 'all'
Requires-Dist: findspark (>=1.3.0) ; extra == 'all'
Requires-Dist: koalas (>=1.8.1) ; extra == 'all'
Requires-Dist: pandas (==1.3.5) ; extra == 'all'
Requires-Dist: dask[complete] (==2021.12.0) ; extra == 'all'
Requires-Dist: distributed (==2021.12.0) ; extra == 'all'
Requires-Dist: dask-ml (>=1.9.0) ; extra == 'all'
Requires-Dist: pyarrow (==1.0.1) ; extra == 'all'
Requires-Dist: coiled (>=0.0.52) ; extra == 'all'
Requires-Dist: psutil (>=5.8.0) ; extra == 'all'
Requires-Dist: vaex (==4.1) ; extra == 'all'
Requires-Dist: gputil ; extra == 'all'
Requires-Dist: numpy (==1.20) ; extra == 'all'
Requires-Dist: tensorflow (==2.9.1) ; extra == 'all'
Requires-Dist: keras (>=2.6.0) ; extra == 'all'
Requires-Dist: nltk (>=3.4.5) ; extra == 'all'
Requires-Dist: sqlalchemy (==1.3.18) ; extra == 'all'
Requires-Dist: flask ; extra == 'all'
Provides-Extra: api
Requires-Dist: flask ; extra == 'api'
Provides-Extra: cudf
Requires-Dist: gputil ; extra == 'cudf'
Requires-Dist: numpy (==1.20) ; extra == 'cudf'
Requires-Dist: distributed (==2021.12.0) ; extra == 'cudf'
Requires-Dist: dask[complete] (==2021.12.0) ; extra == 'cudf'
Provides-Extra: dask
Requires-Dist: dask[complete] (==2021.12.0) ; extra == 'dask'
Requires-Dist: distributed (==2021.12.0) ; extra == 'dask'
Requires-Dist: dask-ml (>=1.9.0) ; extra == 'dask'
Requires-Dist: pyarrow (==1.0.1) ; extra == 'dask'
Requires-Dist: coiled (>=0.0.52) ; extra == 'dask'
Requires-Dist: psutil (>=5.8.0) ; extra == 'dask'
Provides-Extra: db
Requires-Dist: sqlalchemy (==1.3.18) ; extra == 'db'
Provides-Extra: docs
Requires-Dist: sphinx ; extra == 'docs'
Requires-Dist: pytest ; extra == 'docs'
Requires-Dist: mock ; extra == 'docs'
Requires-Dist: nose ; extra == 'docs'
Provides-Extra: lint
Requires-Dist: pep8 ; extra == 'lint'
Requires-Dist: pyflakes ; extra == 'lint'
Provides-Extra: pandas
Requires-Dist: pandas (==1.3.5) ; extra == 'pandas'
Provides-Extra: spark
Requires-Dist: pyspark (>=2.4.1) ; extra == 'spark'
Requires-Dist: findspark (>=1.3.0) ; extra == 'spark'
Requires-Dist: koalas (>=1.8.1) ; extra == 'spark'
Provides-Extra: test
Requires-Dist: pytest ; extra == 'test'
Requires-Dist: mock ; extra == 'test'
Requires-Dist: nose ; extra == 'test'
Provides-Extra: vaex
Requires-Dist: vaex (==4.1) ; extra == 'vaex'
